init_python_package/__init__.py
init_python_package/main.py
init_python_package-0.1.5.dist-info/licenses/LICENSE
init_python_package-0.1.5.dist-info/METADATA
init_python_package-0.1.5.dist-info/WHEEL
init_python_package-0.1.5.dist-info/entry_points.txt
init_python_package-0.1.5.dist-info/top_level.txt
init_python_package-0.1.5.dist-info/RECORD
