Metadata-Version: 2.4
Name: init_python_package
Version: 0.1.5
Summary: A Python package scaffold
Author: George Cutter
License-Expression: Apache-2.0
Classifier: Programming Language :: Python :: 3
Classifier: Operating System :: OS Independent
Requires-Python: >=3.9
License-File: LICENSE
Provides-Extra: dev
Requires-Dist: pytest; extra == "dev"
Requires-Dist: flake8; extra == "dev"
Dynamic: license-file
